README.md
setup.py
apts/__init__.py
apts/catalogs.py
apts/conditions.py
apts/constants.py
apts/equipment.py
apts/messier.py
apts/notify.py
apts/objects.py
apts/observations.py
apts/optics.py
apts/place.py
apts/planets.py
apts/utils.py
apts/weather.py
apts.egg-info/PKG-INFO
apts.egg-info/SOURCES.txt
apts.egg-info/dependency_links.txt
apts.egg-info/requires.txt
apts.egg-info/top_level.txt
apts/models/__init__.py
apts/models/optical.py