Metadata-Version: 1.1
Name: apts
Version: 0.2.13
Summary: Set of tools for automatic astrofotography images aqquisition and processing.
Home-page: http://github.com/pozar87/apts/
Author: Lukasz Pozarlik
Author-email: lpozarlik@gmail.com
License: Apache Software License
Platform: any
Classifier: Programming Language :: Python
Classifier: Development Status :: 1 - Planning
Classifier: Natural Language :: English
Classifier: Environment :: Console
Classifier: Intended Audience :: Developers
Classifier: Intended Audience :: Education
Classifier: License :: OSI Approved :: Apache Software License
Classifier: Operating System :: OS Independent
Classifier: Topic :: Software Development :: Libraries :: Python Modules
